protracker/__init__.py
protracker/crud.py
protracker/database.py
protracker/enums.py
protracker/main.py
protracker/projects.py
protracker/tasks.py
protrack-0.1.0.dist-info/LICENSE
protrack-0.1.0.dist-info/METADATA
protrack-0.1.0.dist-info/WHEEL
protrack-0.1.0.dist-info/entry_points.txt
protrack-0.1.0.dist-info/top_level.txt
protrack-0.1.0.dist-info/RECORD
