Metadata-Version: 2.1
Name: protrack
Version: 0.1.0
Summary: A CLI for keeping track of projects and their tasks
Home-page: https://github.com/Enhancifire/Project-Manager-CLI
Author: Faiz Saiyad
Author-email: fsaiyad990@gmail.com
Classifier: Programming Language :: Python :: 3
Classifier: License :: OSI Approved :: MIT License
Classifier: Operating System :: OS Independent
Requires-Python: >=3.7
License-File: LICENSE
Requires-Dist: sqlalchemy
Requires-Dist: typer
Requires-Dist: rich
Requires-Dist: inquirer
